agro_kit/__init__.py
agro_kit/__main__.py
agro_kit/agro_kit.py
agro_kit/cli.py
agro_kit/demo.py
gps/__init__.py
gps/gps.py
light_sensor/__init__.py
light_sensor/light_sensor.py
moisture_sensor/__init__.py
moisture_sensor/moisture_sensor.py
agro_kit-1.0.2.dist-info/AUTHORS.rst
agro_kit-1.0.2.dist-info/LICENSE
agro_kit-1.0.2.dist-info/METADATA
agro_kit-1.0.2.dist-info/WHEEL
agro_kit-1.0.2.dist-info/entry_points.txt
agro_kit-1.0.2.dist-info/top_level.txt
agro_kit-1.0.2.dist-info/RECORD
