Metadata-Version: 2.1
Name: agro-kit
Version: 1.0.2
Summary: An API to facilitate interaction with an agriculture tech sensor kit.
Home-page: https://github.com/ZidaanHabib/agro_kit
Author: Zidaan Habib, Fraser Montandon
Author-email: hbbzid001@myuct.ac.za
License: GNU General Public License v3
Keywords: agro_kit
Platform: UNKNOWN
Classifier: Development Status :: 2 - Pre-Alpha
Classifier: Intended Audience :: Developers
Classifier: License :: OSI Approved :: GNU General Public License v3 (GPLv3)
Classifier: Natural Language :: English
Classifier: Programming Language :: Python :: 3
Classifier: Programming Language :: Python :: 3.5
Classifier: Programming Language :: Python :: 3.6
Classifier: Programming Language :: Python :: 3.7
Classifier: Programming Language :: Python :: 3.8
Requires-Python: >=3.5
Requires-Dist: Adafruit-GPIO
Requires-Dist: Adafruit-MCP3008
Requires-Dist: file-read-backwards
Requires-Dist: requests
Requires-Dist: pynmea2
Requires-Dist: adafruit-circuitpython-tcs34725
Requires-Dist: RPi.GPIO
Requires-Dist: Adafruit-Blinka
